{"_id":"note:46qWG3-sy","title":"Heroku","content":"Install:\n```\nsudo snap install heroku --classic\n```\n\n<hr>\n\nLogin:\n```\nheroku login\n```\n\n<hr>\n\nClone: \n```\nheroku git:clone -a stark-chamber-36060\n```\n\n<hr>\n\nRe-Connect:\n```\nheroku git:remote --app stark-chamber-36060\n```\n\nconfirm: `git remote -v`\n\n<hr>\n\nRename:\n```\ngit remote rename heroku DoraServer\n```\n\n<hr>\n\nCommit:\n```\ngit add && git commit -m \"my app\" && git push DoraServer main\n```\n\n<hr>\n\nDataBase:\n```\nsudo apt-get install postgresql\n```\nConnect: \n```\nheroku pg:psql --app stark-chamber-36060\n```\n```\nheroku pg:psql --app serene-falls-03482\n```\n\n<hr>\n\nCreate DataBase Add-On:\n\n```\nheroku addons:create --app serene-falls-03482 heroku-postgresql:hobby-dev\n```\n\n<hr>","tags":[],"folderPathname":"/Coding","data":{},"createdAt":"2021-03-01T09:28:10.164Z","updatedAt":"2022-01-28T09:12:21.668Z","trashed":false,"_rev":"xUGOs1Dee"}